{
  "updatedAt": "2026-06-29T22:32:47.590Z",
  "matches": [
    {
      "number": 1,
      "round": "Matchday 1",
      "date": "2026-06-11",
      "kickoff": "2026-06-11T19:00:00.000Z",
      "team1": "Mexico",
      "team2": "South Africa",
      "score": [
        2,
        0
      ],
      "group": "Group A",
      "ground": "Mexico City"
    },
    {
      "number": 2,
      "round": "Matchday 1",
      "date": "2026-06-11",
      "kickoff": "2026-06-12T02:00:00.000Z",
      "team1": "South Korea",
      "team2": "Czech Republic",
      "score": [
        2,
        1
      ],
      "group": "Group A",
      "ground": "Guadalajara (Zapopan)"
    },
    {
      "number": 3,
      "round": "Matchday 8",
      "date": "2026-06-18",
      "kickoff": "2026-06-18T16:00:00.000Z",
      "team1": "Czech Republic",
      "team2": "South Africa",
      "score": [
        1,
        1
      ],
      "group": "Group A",
      "ground": "Atlanta"
    },
    {
      "number": 4,
      "round": "Matchday 8",
      "date": "2026-06-18",
      "kickoff": "2026-06-19T01:00:00.000Z",
      "team1": "Mexico",
      "team2": "South Korea",
      "score": [
        1,
        0
      ],
      "group": "Group A",
      "ground": "Guadalajara (Zapopan)"
    },
    {
      "number": 5,
      "round": "Matchday 14",
      "date": "2026-06-24",
      "kickoff": "2026-06-25T01:00:00.000Z",
      "team1": "Czech Republic",
      "team2": "Mexico",
      "score": [
        0,
        3
      ],
      "group": "Group A",
      "ground": "Mexico City"
    },
    {
      "number": 6,
      "round": "Matchday 14",
      "date": "2026-06-24",
      "kickoff": "2026-06-25T01:00:00.000Z",
      "team1": "South Africa",
      "team2": "South Korea",
      "score": [
        1,
        0
      ],
      "group": "Group A",
      "ground": "Monterrey (Guadalupe)"
    },
    {
      "number": 7,
      "round": "Matchday 2",
      "date": "2026-06-12",
      "kickoff": "2026-06-12T19:00:00.000Z",
      "team1": "Canada",
      "team2": "Bosnia & Herzegovina",
      "score": [
        1,
        1
      ],
      "group": "Group B",
      "ground": "Toronto"
    },
    {
      "number": 8,
      "round": "Matchday 3",
      "date": "2026-06-13",
      "kickoff": "2026-06-13T19:00:00.000Z",
      "team1": "Qatar",
      "team2": "Switzerland",
      "score": [
        1,
        1
      ],
      "group": "Group B",
      "ground": "San Francisco Bay Area (Santa Clara)"
    },
    {
      "number": 9,
      "round": "Matchday 8",
      "date": "2026-06-18",
      "kickoff": "2026-06-18T19:00:00.000Z",
      "team1": "Switzerland",
      "team2": "Bosnia & Herzegovina",
      "score": [
        4,
        1
      ],
      "group": "Group B",
      "ground": "Los Angeles (Inglewood)"
    },
    {
      "number": 10,
      "round": "Matchday 8",
      "date": "2026-06-18",
      "kickoff": "2026-06-18T22:00:00.000Z",
      "team1": "Canada",
      "team2": "Qatar",
      "score": [
        6,
        0
      ],
      "group": "Group B",
      "ground": "Vancouver"
    },
    {
      "number": 11,
      "round": "Matchday 14",
      "date": "2026-06-24",
      "kickoff": "2026-06-24T19:00:00.000Z",
      "team1": "Switzerland",
      "team2": "Canada",
      "score": [
        2,
        1
      ],
      "group": "Group B",
      "ground": "Vancouver"
    },
    {
      "number": 12,
      "round": "Matchday 14",
      "date": "2026-06-24",
      "kickoff": "2026-06-24T19:00:00.000Z",
      "team1": "Bosnia & Herzegovina",
      "team2": "Qatar",
      "score": [
        3,
        1
      ],
      "group": "Group B",
      "ground": "Seattle"
    },
    {
      "number": 13,
      "round": "Matchday 3",
      "date": "2026-06-13",
      "kickoff": "2026-06-13T22:00:00.000Z",
      "team1": "Brazil",
      "team2": "Morocco",
      "score": [
        1,
        1
      ],
      "group": "Group C",
      "ground": "New York/New Jersey (East Rutherford)"
    },
    {
      "number": 14,
      "round": "Matchday 3",
      "date": "2026-06-13",
      "kickoff": "2026-06-14T01:00:00.000Z",
      "team1": "Haiti",
      "team2": "Scotland",
      "score": [
        0,
        1
      ],
      "group": "Group C",
      "ground": "Boston (Foxborough)"
    },
    {
      "number": 15,
      "round": "Matchday 9",
      "date": "2026-06-19",
      "kickoff": "2026-06-19T22:00:00.000Z",
      "team1": "Scotland",
      "team2": "Morocco",
      "score": [
        0,
        1
      ],
      "group": "Group C",
      "ground": "Boston (Foxborough)"
    },
    {
      "number": 16,
      "round": "Matchday 9",
      "date": "2026-06-19",
      "kickoff": "2026-06-20T00:30:00.000Z",
      "team1": "Brazil",
      "team2": "Haiti",
      "score": [
        3,
        0
      ],
      "group": "Group C",
      "ground": "Philadelphia"
    },
    {
      "number": 17,
      "round": "Matchday 14",
      "date": "2026-06-24",
      "kickoff": "2026-06-24T22:00:00.000Z",
      "team1": "Scotland",
      "team2": "Brazil",
      "score": [
        0,
        3
      ],
      "group": "Group C",
      "ground": "Miami (Miami Gardens)"
    },
    {
      "number": 18,
      "round": "Matchday 14",
      "date": "2026-06-24",
      "kickoff": "2026-06-24T22:00:00.000Z",
      "team1": "Morocco",
      "team2": "Haiti",
      "score": [
        4,
        2
      ],
      "group": "Group C",
      "ground": "Atlanta"
    },
    {
      "number": 19,
      "round": "Matchday 2",
      "date": "2026-06-12",
      "kickoff": "2026-06-13T01:00:00.000Z",
      "team1": "USA",
      "team2": "Paraguay",
      "score": [
        4,
        1
      ],
      "group": "Group D",
      "ground": "Los Angeles (Inglewood)"
    },
    {
      "number": 20,
      "round": "Matchday 3",
      "date": "2026-06-13",
      "kickoff": "2026-06-14T04:00:00.000Z",
      "team1": "Australia",
      "team2": "Turkey",
      "score": [
        2,
        0
      ],
      "group": "Group D",
      "ground": "Vancouver"
    },
    {
      "number": 21,
      "round": "Matchday 9",
      "date": "2026-06-19",
      "kickoff": "2026-06-19T19:00:00.000Z",
      "team1": "USA",
      "team2": "Australia",
      "score": [
        2,
        0
      ],
      "group": "Group D",
      "ground": "Seattle"
    },
    {
      "number": 22,
      "round": "Matchday 9",
      "date": "2026-06-19",
      "kickoff": "2026-06-20T03:00:00.000Z",
      "team1": "Turkey",
      "team2": "Paraguay",
      "score": [
        0,
        1
      ],
      "group": "Group D",
      "ground": "San Francisco Bay Area (Santa Clara)"
    },
    {
      "number": 23,
      "round": "Matchday 15",
      "date": "2026-06-25",
      "kickoff": "2026-06-26T02:00:00.000Z",
      "team1": "Turkey",
      "team2": "USA",
      "score": [
        3,
        2
      ],
      "group": "Group D",
      "ground": "Los Angeles (Inglewood)"
    },
    {
      "number": 24,
      "round": "Matchday 15",
      "date": "2026-06-25",
      "kickoff": "2026-06-26T02:00:00.000Z",
      "team1": "Paraguay",
      "team2": "Australia",
      "score": [
        0,
        0
      ],
      "group": "Group D",
      "ground": "San Francisco Bay Area (Santa Clara)"
    },
    {
      "number": 25,
      "round": "Matchday 4",
      "date": "2026-06-14",
      "kickoff": "2026-06-14T17:00:00.000Z",
      "team1": "Germany",
      "team2": "Curaçao",
      "score": [
        7,
        1
      ],
      "group": "Group E",
      "ground": "Houston"
    },
    {
      "number": 26,
      "round": "Matchday 4",
      "date": "2026-06-14",
      "kickoff": "2026-06-14T23:00:00.000Z",
      "team1": "Ivory Coast",
      "team2": "Ecuador",
      "score": [
        1,
        0
      ],
      "group": "Group E",
      "ground": "Philadelphia"
    },
    {
      "number": 27,
      "round": "Matchday 10",
      "date": "2026-06-20",
      "kickoff": "2026-06-20T20:00:00.000Z",
      "team1": "Germany",
      "team2": "Ivory Coast",
      "score": [
        2,
        1
      ],
      "group": "Group E",
      "ground": "Toronto"
    },
    {
      "number": 28,
      "round": "Matchday 10",
      "date": "2026-06-20",
      "kickoff": "2026-06-21T00:00:00.000Z",
      "team1": "Ecuador",
      "team2": "Curaçao",
      "score": [
        0,
        0
      ],
      "group": "Group E",
      "ground": "Kansas City"
    },
    {
      "number": 29,
      "round": "Matchday 15",
      "date": "2026-06-25",
      "kickoff": "2026-06-25T20:00:00.000Z",
      "team1": "Curaçao",
      "team2": "Ivory Coast",
      "score": [
        0,
        2
      ],
      "group": "Group E",
      "ground": "Philadelphia"
    },
    {
      "number": 30,
      "round": "Matchday 15",
      "date": "2026-06-25",
      "kickoff": "2026-06-25T20:00:00.000Z",
      "team1": "Ecuador",
      "team2": "Germany",
      "score": [
        2,
        1
      ],
      "group": "Group E",
      "ground": "New York/New Jersey (East Rutherford)"
    },
    {
      "number": 31,
      "round": "Matchday 4",
      "date": "2026-06-14",
      "kickoff": "2026-06-14T20:00:00.000Z",
      "team1": "Netherlands",
      "team2": "Japan",
      "score": [
        2,
        2
      ],
      "group": "Group F",
      "ground": "Dallas (Arlington)"
    },
    {
      "number": 32,
      "round": "Matchday 4",
      "date": "2026-06-14",
      "kickoff": "2026-06-15T02:00:00.000Z",
      "team1": "Sweden",
      "team2": "Tunisia",
      "score": [
        5,
        1
      ],
      "group": "Group F",
      "ground": "Monterrey (Guadalupe)"
    },
    {
      "number": 33,
      "round": "Matchday 10",
      "date": "2026-06-20",
      "kickoff": "2026-06-20T17:00:00.000Z",
      "team1": "Netherlands",
      "team2": "Sweden",
      "score": [
        5,
        1
      ],
      "group": "Group F",
      "ground": "Houston"
    },
    {
      "number": 34,
      "round": "Matchday 10",
      "date": "2026-06-20",
      "kickoff": "2026-06-21T04:00:00.000Z",
      "team1": "Tunisia",
      "team2": "Japan",
      "score": [
        0,
        4
      ],
      "group": "Group F",
      "ground": "Monterrey (Guadalupe)"
    },
    {
      "number": 35,
      "round": "Matchday 15",
      "date": "2026-06-25",
      "kickoff": "2026-06-25T23:00:00.000Z",
      "team1": "Japan",
      "team2": "Sweden",
      "score": [
        1,
        1
      ],
      "group": "Group F",
      "ground": "Dallas (Arlington)"
    },
    {
      "number": 36,
      "round": "Matchday 15",
      "date": "2026-06-25",
      "kickoff": "2026-06-25T23:00:00.000Z",
      "team1": "Tunisia",
      "team2": "Netherlands",
      "score": [
        1,
        3
      ],
      "group": "Group F",
      "ground": "Kansas City"
    },
    {
      "number": 37,
      "round": "Matchday 5",
      "date": "2026-06-15",
      "kickoff": "2026-06-15T19:00:00.000Z",
      "team1": "Belgium",
      "team2": "Egypt",
      "score": [
        1,
        1
      ],
      "group": "Group G",
      "ground": "Seattle"
    },
    {
      "number": 38,
      "round": "Matchday 5",
      "date": "2026-06-15",
      "kickoff": "2026-06-16T01:00:00.000Z",
      "team1": "Iran",
      "team2": "New Zealand",
      "score": [
        2,
        2
      ],
      "group": "Group G",
      "ground": "Los Angeles (Inglewood)"
    },
    {
      "number": 39,
      "round": "Matchday 11",
      "date": "2026-06-21",
      "kickoff": "2026-06-21T19:00:00.000Z",
      "team1": "Belgium",
      "team2": "Iran",
      "score": [
        0,
        0
      ],
      "group": "Group G",
      "ground": "Los Angeles (Inglewood)"
    },
    {
      "number": 40,
      "round": "Matchday 11",
      "date": "2026-06-21",
      "kickoff": "2026-06-22T01:00:00.000Z",
      "team1": "New Zealand",
      "team2": "Egypt",
      "score": [
        1,
        3
      ],
      "group": "Group G",
      "ground": "Vancouver"
    },
    {
      "number": 41,
      "round": "Matchday 16",
      "date": "2026-06-26",
      "kickoff": "2026-06-27T03:00:00.000Z",
      "team1": "Egypt",
      "team2": "Iran",
      "score": [
        1,
        1
      ],
      "group": "Group G",
      "ground": "Seattle"
    },
    {
      "number": 42,
      "round": "Matchday 16",
      "date": "2026-06-26",
      "kickoff": "2026-06-27T03:00:00.000Z",
      "team1": "New Zealand",
      "team2": "Belgium",
      "score": [
        1,
        5
      ],
      "group": "Group G",
      "ground": "Vancouver"
    },
    {
      "number": 43,
      "round": "Matchday 5",
      "date": "2026-06-15",
      "kickoff": "2026-06-15T16:00:00.000Z",
      "team1": "Spain",
      "team2": "Cape Verde",
      "score": [
        0,
        0
      ],
      "group": "Group H",
      "ground": "Atlanta"
    },
    {
      "number": 44,
      "round": "Matchday 5",
      "date": "2026-06-15",
      "kickoff": "2026-06-15T22:00:00.000Z",
      "team1": "Saudi Arabia",
      "team2": "Uruguay",
      "score": [
        1,
        1
      ],
      "group": "Group H",
      "ground": "Miami (Miami Gardens)"
    },
    {
      "number": 45,
      "round": "Matchday 11",
      "date": "2026-06-21",
      "kickoff": "2026-06-21T16:00:00.000Z",
      "team1": "Spain",
      "team2": "Saudi Arabia",
      "score": [
        4,
        0
      ],
      "group": "Group H",
      "ground": "Atlanta"
    },
    {
      "number": 46,
      "round": "Matchday 11",
      "date": "2026-06-21",
      "kickoff": "2026-06-21T22:00:00.000Z",
      "team1": "Uruguay",
      "team2": "Cape Verde",
      "score": [
        2,
        2
      ],
      "group": "Group H",
      "ground": "Miami (Miami Gardens)"
    },
    {
      "number": 47,
      "round": "Matchday 16",
      "date": "2026-06-26",
      "kickoff": "2026-06-27T00:00:00.000Z",
      "team1": "Cape Verde",
      "team2": "Saudi Arabia",
      "score": [
        0,
        0
      ],
      "group": "Group H",
      "ground": "Houston"
    },
    {
      "number": 48,
      "round": "Matchday 16",
      "date": "2026-06-26",
      "kickoff": "2026-06-27T00:00:00.000Z",
      "team1": "Uruguay",
      "team2": "Spain",
      "score": [
        0,
        1
      ],
      "group": "Group H",
      "ground": "Guadalajara (Zapopan)"
    },
    {
      "number": 49,
      "round": "Matchday 6",
      "date": "2026-06-16",
      "kickoff": "2026-06-16T19:00:00.000Z",
      "team1": "France",
      "team2": "Senegal",
      "score": [
        3,
        1
      ],
      "group": "Group I",
      "ground": "New York/New Jersey (East Rutherford)"
    },
    {
      "number": 50,
      "round": "Matchday 6",
      "date": "2026-06-16",
      "kickoff": "2026-06-16T22:00:00.000Z",
      "team1": "Iraq",
      "team2": "Norway",
      "score": [
        1,
        4
      ],
      "group": "Group I",
      "ground": "Boston (Foxborough)"
    },
    {
      "number": 51,
      "round": "Matchday 12",
      "date": "2026-06-22",
      "kickoff": "2026-06-22T21:00:00.000Z",
      "team1": "France",
      "team2": "Iraq",
      "score": [
        3,
        0
      ],
      "group": "Group I",
      "ground": "Philadelphia"
    },
    {
      "number": 52,
      "round": "Matchday 12",
      "date": "2026-06-22",
      "kickoff": "2026-06-23T00:00:00.000Z",
      "team1": "Norway",
      "team2": "Senegal",
      "score": [
        3,
        2
      ],
      "group": "Group I",
      "ground": "New York/New Jersey (East Rutherford)"
    },
    {
      "number": 53,
      "round": "Matchday 16",
      "date": "2026-06-26",
      "kickoff": "2026-06-26T19:00:00.000Z",
      "team1": "Norway",
      "team2": "France",
      "score": [
        1,
        4
      ],
      "group": "Group I",
      "ground": "Boston (Foxborough)"
    },
    {
      "number": 54,
      "round": "Matchday 16",
      "date": "2026-06-26",
      "kickoff": "2026-06-26T19:00:00.000Z",
      "team1": "Senegal",
      "team2": "Iraq",
      "score": [
        5,
        0
      ],
      "group": "Group I",
      "ground": "Toronto"
    },
    {
      "number": 55,
      "round": "Matchday 6",
      "date": "2026-06-16",
      "kickoff": "2026-06-17T01:00:00.000Z",
      "team1": "Argentina",
      "team2": "Algeria",
      "score": [
        3,
        0
      ],
      "group": "Group J",
      "ground": "Kansas City"
    },
    {
      "number": 56,
      "round": "Matchday 6",
      "date": "2026-06-16",
      "kickoff": "2026-06-17T04:00:00.000Z",
      "team1": "Austria",
      "team2": "Jordan",
      "score": [
        3,
        1
      ],
      "group": "Group J",
      "ground": "San Francisco Bay Area (Santa Clara)"
    },
    {
      "number": 57,
      "round": "Matchday 12",
      "date": "2026-06-22",
      "kickoff": "2026-06-22T17:00:00.000Z",
      "team1": "Argentina",
      "team2": "Austria",
      "score": [
        2,
        0
      ],
      "group": "Group J",
      "ground": "Dallas (Arlington)"
    },
    {
      "number": 58,
      "round": "Matchday 12",
      "date": "2026-06-22",
      "kickoff": "2026-06-23T03:00:00.000Z",
      "team1": "Jordan",
      "team2": "Algeria",
      "score": [
        1,
        2
      ],
      "group": "Group J",
      "ground": "San Francisco Bay Area (Santa Clara)"
    },
    {
      "number": 59,
      "round": "Matchday 17",
      "date": "2026-06-27",
      "kickoff": "2026-06-28T02:00:00.000Z",
      "team1": "Algeria",
      "team2": "Austria",
      "score": [
        3,
        3
      ],
      "group": "Group J",
      "ground": "Kansas City"
    },
    {
      "number": 60,
      "round": "Matchday 17",
      "date": "2026-06-27",
      "kickoff": "2026-06-28T02:00:00.000Z",
      "team1": "Jordan",
      "team2": "Argentina",
      "score": [
        1,
        3
      ],
      "group": "Group J",
      "ground": "Dallas (Arlington)"
    },
    {
      "number": 61,
      "round": "Matchday 7",
      "date": "2026-06-17",
      "kickoff": "2026-06-17T17:00:00.000Z",
      "team1": "Portugal",
      "team2": "DR Congo",
      "score": [
        1,
        1
      ],
      "group": "Group K",
      "ground": "Houston"
    },
    {
      "number": 62,
      "round": "Matchday 7",
      "date": "2026-06-17",
      "kickoff": "2026-06-18T02:00:00.000Z",
      "team1": "Uzbekistan",
      "team2": "Colombia",
      "score": [
        1,
        3
      ],
      "group": "Group K",
      "ground": "Mexico City"
    },
    {
      "number": 63,
      "round": "Matchday 13",
      "date": "2026-06-23",
      "kickoff": "2026-06-23T17:00:00.000Z",
      "team1": "Portugal",
      "team2": "Uzbekistan",
      "score": [
        5,
        0
      ],
      "group": "Group K",
      "ground": "Houston"
    },
    {
      "number": 64,
      "round": "Matchday 13",
      "date": "2026-06-23",
      "kickoff": "2026-06-24T02:00:00.000Z",
      "team1": "Colombia",
      "team2": "DR Congo",
      "score": [
        1,
        0
      ],
      "group": "Group K",
      "ground": "Guadalajara (Zapopan)"
    },
    {
      "number": 65,
      "round": "Matchday 17",
      "date": "2026-06-27",
      "kickoff": "2026-06-27T23:30:00.000Z",
      "team1": "Colombia",
      "team2": "Portugal",
      "score": [
        0,
        0
      ],
      "group": "Group K",
      "ground": "Miami (Miami Gardens)"
    },
    {
      "number": 66,
      "round": "Matchday 17",
      "date": "2026-06-27",
      "kickoff": "2026-06-27T23:30:00.000Z",
      "team1": "DR Congo",
      "team2": "Uzbekistan",
      "score": [
        3,
        1
      ],
      "group": "Group K",
      "ground": "Atlanta"
    },
    {
      "number": 67,
      "round": "Matchday 7",
      "date": "2026-06-17",
      "kickoff": "2026-06-17T20:00:00.000Z",
      "team1": "England",
      "team2": "Croatia",
      "score": [
        4,
        2
      ],
      "group": "Group L",
      "ground": "Dallas (Arlington)"
    },
    {
      "number": 68,
      "round": "Matchday 7",
      "date": "2026-06-17",
      "kickoff": "2026-06-17T23:00:00.000Z",
      "team1": "Ghana",
      "team2": "Panama",
      "score": [
        1,
        0
      ],
      "group": "Group L",
      "ground": "Toronto"
    },
    {
      "number": 69,
      "round": "Matchday 13",
      "date": "2026-06-23",
      "kickoff": "2026-06-23T20:00:00.000Z",
      "team1": "England",
      "team2": "Ghana",
      "score": [
        0,
        0
      ],
      "group": "Group L",
      "ground": "Boston (Foxborough)"
    },
    {
      "number": 70,
      "round": "Matchday 13",
      "date": "2026-06-23",
      "kickoff": "2026-06-23T23:00:00.000Z",
      "team1": "Panama",
      "team2": "Croatia",
      "score": [
        0,
        1
      ],
      "group": "Group L",
      "ground": "Toronto"
    },
    {
      "number": 71,
      "round": "Matchday 17",
      "date": "2026-06-27",
      "kickoff": "2026-06-27T21:00:00.000Z",
      "team1": "Panama",
      "team2": "England",
      "score": [
        0,
        2
      ],
      "group": "Group L",
      "ground": "New York/New Jersey (East Rutherford)"
    },
    {
      "number": 72,
      "round": "Matchday 17",
      "date": "2026-06-27",
      "kickoff": "2026-06-27T21:00:00.000Z",
      "team1": "Croatia",
      "team2": "Ghana",
      "score": [
        2,
        1
      ],
      "group": "Group L",
      "ground": "Philadelphia"
    },
    {
      "number": 73,
      "round": "Round of 32",
      "date": "2026-06-28",
      "kickoff": "2026-06-28T19:00:00.000Z",
      "team1": "South Africa",
      "team2": "Canada",
      "score": [
        0,
        1
      ],
      "ground": "Los Angeles (Inglewood)"
    },
    {
      "number": 74,
      "round": "Round of 32",
      "date": "2026-06-29",
      "kickoff": "2026-06-29T20:30:00.000Z",
      "team1": "Germany",
      "team2": "Paraguay",
      "ground": "Boston (Foxborough)"
    },
    {
      "number": 75,
      "round": "Round of 32",
      "date": "2026-06-29",
      "kickoff": "2026-06-30T01:00:00.000Z",
      "team1": "Netherlands",
      "team2": "Morocco",
      "ground": "Monterrey (Guadalupe)"
    },
    {
      "number": 76,
      "round": "Round of 32",
      "date": "2026-06-29",
      "kickoff": "2026-06-29T17:00:00.000Z",
      "team1": "Brazil",
      "team2": "Japan",
      "score": [
        2,
        1
      ],
      "ground": "Houston"
    },
    {
      "number": 77,
      "round": "Round of 32",
      "date": "2026-06-30",
      "kickoff": "2026-06-30T21:00:00.000Z",
      "team1": "France",
      "team2": "Sweden",
      "ground": "New York/New Jersey (East Rutherford)"
    },
    {
      "number": 78,
      "round": "Round of 32",
      "date": "2026-06-30",
      "kickoff": "2026-06-30T17:00:00.000Z",
      "team1": "Ivory Coast",
      "team2": "Norway",
      "ground": "Dallas (Arlington)"
    },
    {
      "number": 79,
      "round": "Round of 32",
      "date": "2026-06-30",
      "kickoff": "2026-07-01T01:00:00.000Z",
      "team1": "Mexico",
      "team2": "Ecuador",
      "ground": "Mexico City"
    },
    {
      "number": 80,
      "round": "Round of 32",
      "date": "2026-07-01",
      "kickoff": "2026-07-01T16:00:00.000Z",
      "team1": "England",
      "team2": "DR Congo",
      "ground": "Atlanta"
    },
    {
      "number": 81,
      "round": "Round of 32",
      "date": "2026-07-01",
      "kickoff": "2026-07-02T00:00:00.000Z",
      "team1": "USA",
      "team2": "Bosnia & Herzegovina",
      "ground": "San Francisco Bay Area (Santa Clara)"
    },
    {
      "number": 82,
      "round": "Round of 32",
      "date": "2026-07-01",
      "kickoff": "2026-07-01T20:00:00.000Z",
      "team1": "Belgium",
      "team2": "Senegal",
      "ground": "Seattle"
    },
    {
      "number": 83,
      "round": "Round of 32",
      "date": "2026-07-02",
      "kickoff": "2026-07-02T23:00:00.000Z",
      "team1": "Portugal",
      "team2": "Croatia",
      "ground": "Toronto"
    },
    {
      "number": 84,
      "round": "Round of 32",
      "date": "2026-07-02",
      "kickoff": "2026-07-02T19:00:00.000Z",
      "team1": "Spain",
      "team2": "Austria",
      "ground": "Los Angeles (Inglewood)"
    },
    {
      "number": 85,
      "round": "Round of 32",
      "date": "2026-07-02",
      "kickoff": "2026-07-03T03:00:00.000Z",
      "team1": "Switzerland",
      "team2": "Algeria",
      "ground": "Vancouver"
    },
    {
      "number": 86,
      "round": "Round of 32",
      "date": "2026-07-03",
      "kickoff": "2026-07-03T22:00:00.000Z",
      "team1": "Argentina",
      "team2": "Cape Verde",
      "ground": "Miami (Miami Gardens)"
    },
    {
      "number": 87,
      "round": "Round of 32",
      "date": "2026-07-03",
      "kickoff": "2026-07-04T01:30:00.000Z",
      "team1": "Colombia",
      "team2": "Ghana",
      "ground": "Kansas City"
    },
    {
      "number": 88,
      "round": "Round of 32",
      "date": "2026-07-03",
      "kickoff": "2026-07-03T18:00:00.000Z",
      "team1": "Australia",
      "team2": "Egypt",
      "ground": "Dallas (Arlington)"
    },
    {
      "number": 89,
      "round": "Round of 16",
      "date": "2026-07-04",
      "kickoff": "2026-07-04T21:00:00.000Z",
      "team1": "W74",
      "team2": "W77",
      "ground": "Philadelphia"
    },
    {
      "number": 90,
      "round": "Round of 16",
      "date": "2026-07-04",
      "kickoff": "2026-07-04T17:00:00.000Z",
      "team1": "Canada",
      "team2": "W75",
      "ground": "Houston"
    },
    {
      "number": 91,
      "round": "Round of 16",
      "date": "2026-07-05",
      "kickoff": "2026-07-05T20:00:00.000Z",
      "team1": "W76",
      "team2": "W78",
      "ground": "New York/New Jersey (East Rutherford)"
    },
    {
      "number": 92,
      "round": "Round of 16",
      "date": "2026-07-05",
      "kickoff": "2026-07-06T00:00:00.000Z",
      "team1": "W79",
      "team2": "W80",
      "ground": "Mexico City"
    },
    {
      "number": 93,
      "round": "Round of 16",
      "date": "2026-07-06",
      "kickoff": "2026-07-06T19:00:00.000Z",
      "team1": "W83",
      "team2": "W84",
      "ground": "Dallas (Arlington)"
    },
    {
      "number": 94,
      "round": "Round of 16",
      "date": "2026-07-06",
      "kickoff": "2026-07-07T00:00:00.000Z",
      "team1": "W81",
      "team2": "W82",
      "ground": "Seattle"
    },
    {
      "number": 95,
      "round": "Round of 16",
      "date": "2026-07-07",
      "kickoff": "2026-07-07T16:00:00.000Z",
      "team1": "W86",
      "team2": "W88",
      "ground": "Atlanta"
    },
    {
      "number": 96,
      "round": "Round of 16",
      "date": "2026-07-07",
      "kickoff": "2026-07-07T20:00:00.000Z",
      "team1": "W85",
      "team2": "W87",
      "ground": "Vancouver"
    },
    {
      "number": 97,
      "round": "Quarter-final",
      "date": "2026-07-09",
      "kickoff": "2026-07-09T20:00:00.000Z",
      "team1": "W89",
      "team2": "W90",
      "ground": "Boston (Foxborough)"
    },
    {
      "number": 98,
      "round": "Quarter-final",
      "date": "2026-07-10",
      "kickoff": "2026-07-10T19:00:00.000Z",
      "team1": "W93",
      "team2": "W94",
      "ground": "Los Angeles (Inglewood)"
    },
    {
      "number": 99,
      "round": "Quarter-final",
      "date": "2026-07-11",
      "kickoff": "2026-07-11T21:00:00.000Z",
      "team1": "W91",
      "team2": "W92",
      "ground": "Miami (Miami Gardens)"
    },
    {
      "number": 100,
      "round": "Quarter-final",
      "date": "2026-07-11",
      "kickoff": "2026-07-12T01:00:00.000Z",
      "team1": "W95",
      "team2": "W96",
      "ground": "Kansas City"
    },
    {
      "number": 101,
      "round": "Semi-final",
      "date": "2026-07-14",
      "kickoff": "2026-07-14T19:00:00.000Z",
      "team1": "W97",
      "team2": "W98",
      "ground": "Dallas (Arlington)"
    },
    {
      "number": 102,
      "round": "Semi-final",
      "date": "2026-07-15",
      "kickoff": "2026-07-15T19:00:00.000Z",
      "team1": "W99",
      "team2": "W100",
      "ground": "Atlanta"
    },
    {
      "number": 103,
      "round": "Match for third place",
      "date": "2026-07-18",
      "kickoff": "2026-07-18T21:00:00.000Z",
      "team1": "L101",
      "team2": "L102",
      "ground": "Miami (Miami Gardens)"
    },
    {
      "number": 104,
      "round": "Final",
      "date": "2026-07-19",
      "kickoff": "2026-07-19T19:00:00.000Z",
      "team1": "W101",
      "team2": "W102",
      "ground": "New York/New Jersey (East Rutherford)"
    }
  ],
  "groups": [
    {
      "name": "Group A",
      "teams": [
        {
          "team": "Mexico",
          "played": 3,
          "won": 3,
          "drawn": 0,
          "lost": 0,
          "gf": 6,
          "ga": 0,
          "points": 9
        },
        {
          "team": "South Africa",
          "played": 3,
          "won": 1,
          "drawn": 1,
          "lost": 1,
          "gf": 2,
          "ga": 3,
          "points": 4
        },
        {
          "team": "South Korea",
          "played": 3,
          "won": 1,
          "drawn": 0,
          "lost": 2,
          "gf": 2,
          "ga": 3,
          "points": 3
        },
        {
          "team": "Czech Republic",
          "played": 3,
          "won": 0,
          "drawn": 1,
          "lost": 2,
          "gf": 2,
          "ga": 6,
          "points": 1
        }
      ]
    },
    {
      "name": "Group B",
      "teams": [
        {
          "team": "Switzerland",
          "played": 3,
          "won": 2,
          "drawn": 1,
          "lost": 0,
          "gf": 7,
          "ga": 3,
          "points": 7
        },
        {
          "team": "Canada",
          "played": 3,
          "won": 1,
          "drawn": 1,
          "lost": 1,
          "gf": 8,
          "ga": 3,
          "points": 4
        },
        {
          "team": "Bosnia & Herzegovina",
          "played": 3,
          "won": 1,
          "drawn": 1,
          "lost": 1,
          "gf": 5,
          "ga": 6,
          "points": 4
        },
        {
          "team": "Qatar",
          "played": 3,
          "won": 0,
          "drawn": 1,
          "lost": 2,
          "gf": 2,
          "ga": 10,
          "points": 1
        }
      ]
    },
    {
      "name": "Group C",
      "teams": [
        {
          "team": "Brazil",
          "played": 3,
          "won": 2,
          "drawn": 1,
          "lost": 0,
          "gf": 7,
          "ga": 1,
          "points": 7
        },
        {
          "team": "Morocco",
          "played": 3,
          "won": 2,
          "drawn": 1,
          "lost": 0,
          "gf": 6,
          "ga": 3,
          "points": 7
        },
        {
          "team": "Scotland",
          "played": 3,
          "won": 1,
          "drawn": 0,
          "lost": 2,
          "gf": 1,
          "ga": 4,
          "points": 3
        },
        {
          "team": "Haiti",
          "played": 3,
          "won": 0,
          "drawn": 0,
          "lost": 3,
          "gf": 2,
          "ga": 8,
          "points": 0
        }
      ]
    },
    {
      "name": "Group D",
      "teams": [
        {
          "team": "USA",
          "played": 3,
          "won": 2,
          "drawn": 0,
          "lost": 1,
          "gf": 8,
          "ga": 4,
          "points": 6
        },
        {
          "team": "Australia",
          "played": 3,
          "won": 1,
          "drawn": 1,
          "lost": 1,
          "gf": 2,
          "ga": 2,
          "points": 4
        },
        {
          "team": "Paraguay",
          "played": 3,
          "won": 1,
          "drawn": 1,
          "lost": 1,
          "gf": 2,
          "ga": 4,
          "points": 4
        },
        {
          "team": "Turkey",
          "played": 3,
          "won": 1,
          "drawn": 0,
          "lost": 2,
          "gf": 3,
          "ga": 5,
          "points": 3
        }
      ]
    },
    {
      "name": "Group E",
      "teams": [
        {
          "team": "Germany",
          "played": 3,
          "won": 2,
          "drawn": 0,
          "lost": 1,
          "gf": 10,
          "ga": 4,
          "points": 6
        },
        {
          "team": "Ivory Coast",
          "played": 3,
          "won": 2,
          "drawn": 0,
          "lost": 1,
          "gf": 4,
          "ga": 2,
          "points": 6
        },
        {
          "team": "Ecuador",
          "played": 3,
          "won": 1,
          "drawn": 1,
          "lost": 1,
          "gf": 2,
          "ga": 2,
          "points": 4
        },
        {
          "team": "Curaçao",
          "played": 3,
          "won": 0,
          "drawn": 1,
          "lost": 2,
          "gf": 1,
          "ga": 9,
          "points": 1
        }
      ]
    },
    {
      "name": "Group F",
      "teams": [
        {
          "team": "Netherlands",
          "played": 3,
          "won": 2,
          "drawn": 1,
          "lost": 0,
          "gf": 10,
          "ga": 4,
          "points": 7
        },
        {
          "team": "Japan",
          "played": 3,
          "won": 1,
          "drawn": 2,
          "lost": 0,
          "gf": 7,
          "ga": 3,
          "points": 5
        },
        {
          "team": "Sweden",
          "played": 3,
          "won": 1,
          "drawn": 1,
          "lost": 1,
          "gf": 7,
          "ga": 7,
          "points": 4
        },
        {
          "team": "Tunisia",
          "played": 3,
          "won": 0,
          "drawn": 0,
          "lost": 3,
          "gf": 2,
          "ga": 12,
          "points": 0
        }
      ]
    },
    {
      "name": "Group G",
      "teams": [
        {
          "team": "Belgium",
          "played": 3,
          "won": 1,
          "drawn": 2,
          "lost": 0,
          "gf": 6,
          "ga": 2,
          "points": 5
        },
        {
          "team": "Egypt",
          "played": 3,
          "won": 1,
          "drawn": 2,
          "lost": 0,
          "gf": 5,
          "ga": 3,
          "points": 5
        },
        {
          "team": "Iran",
          "played": 3,
          "won": 0,
          "drawn": 3,
          "lost": 0,
          "gf": 3,
          "ga": 3,
          "points": 3
        },
        {
          "team": "New Zealand",
          "played": 3,
          "won": 0,
          "drawn": 1,
          "lost": 2,
          "gf": 4,
          "ga": 10,
          "points": 1
        }
      ]
    },
    {
      "name": "Group H",
      "teams": [
        {
          "team": "Spain",
          "played": 3,
          "won": 2,
          "drawn": 1,
          "lost": 0,
          "gf": 5,
          "ga": 0,
          "points": 7
        },
        {
          "team": "Cape Verde",
          "played": 3,
          "won": 0,
          "drawn": 3,
          "lost": 0,
          "gf": 2,
          "ga": 2,
          "points": 3
        },
        {
          "team": "Uruguay",
          "played": 3,
          "won": 0,
          "drawn": 2,
          "lost": 1,
          "gf": 3,
          "ga": 4,
          "points": 2
        },
        {
          "team": "Saudi Arabia",
          "played": 3,
          "won": 0,
          "drawn": 2,
          "lost": 1,
          "gf": 1,
          "ga": 5,
          "points": 2
        }
      ]
    },
    {
      "name": "Group I",
      "teams": [
        {
          "team": "France",
          "played": 3,
          "won": 3,
          "drawn": 0,
          "lost": 0,
          "gf": 10,
          "ga": 2,
          "points": 9
        },
        {
          "team": "Norway",
          "played": 3,
          "won": 2,
          "drawn": 0,
          "lost": 1,
          "gf": 8,
          "ga": 7,
          "points": 6
        },
        {
          "team": "Senegal",
          "played": 3,
          "won": 1,
          "drawn": 0,
          "lost": 2,
          "gf": 8,
          "ga": 6,
          "points": 3
        },
        {
          "team": "Iraq",
          "played": 3,
          "won": 0,
          "drawn": 0,
          "lost": 3,
          "gf": 1,
          "ga": 12,
          "points": 0
        }
      ]
    },
    {
      "name": "Group J",
      "teams": [
        {
          "team": "Argentina",
          "played": 3,
          "won": 3,
          "drawn": 0,
          "lost": 0,
          "gf": 8,
          "ga": 1,
          "points": 9
        },
        {
          "team": "Austria",
          "played": 3,
          "won": 1,
          "drawn": 1,
          "lost": 1,
          "gf": 6,
          "ga": 6,
          "points": 4
        },
        {
          "team": "Algeria",
          "played": 3,
          "won": 1,
          "drawn": 1,
          "lost": 1,
          "gf": 5,
          "ga": 7,
          "points": 4
        },
        {
          "team": "Jordan",
          "played": 3,
          "won": 0,
          "drawn": 0,
          "lost": 3,
          "gf": 3,
          "ga": 8,
          "points": 0
        }
      ]
    },
    {
      "name": "Group K",
      "teams": [
        {
          "team": "Colombia",
          "played": 3,
          "won": 2,
          "drawn": 1,
          "lost": 0,
          "gf": 4,
          "ga": 1,
          "points": 7
        },
        {
          "team": "Portugal",
          "played": 3,
          "won": 1,
          "drawn": 2,
          "lost": 0,
          "gf": 6,
          "ga": 1,
          "points": 5
        },
        {
          "team": "DR Congo",
          "played": 3,
          "won": 1,
          "drawn": 1,
          "lost": 1,
          "gf": 4,
          "ga": 3,
          "points": 4
        },
        {
          "team": "Uzbekistan",
          "played": 3,
          "won": 0,
          "drawn": 0,
          "lost": 3,
          "gf": 2,
          "ga": 11,
          "points": 0
        }
      ]
    },
    {
      "name": "Group L",
      "teams": [
        {
          "team": "England",
          "played": 3,
          "won": 2,
          "drawn": 1,
          "lost": 0,
          "gf": 6,
          "ga": 2,
          "points": 7
        },
        {
          "team": "Croatia",
          "played": 3,
          "won": 2,
          "drawn": 0,
          "lost": 1,
          "gf": 5,
          "ga": 5,
          "points": 6
        },
        {
          "team": "Ghana",
          "played": 3,
          "won": 1,
          "drawn": 1,
          "lost": 1,
          "gf": 2,
          "ga": 2,
          "points": 4
        },
        {
          "team": "Panama",
          "played": 3,
          "won": 0,
          "drawn": 0,
          "lost": 3,
          "gf": 0,
          "ga": 4,
          "points": 0
        }
      ]
    }
  ],
  "scorers": [
    {
      "name": "Lionel Messi",
      "team": "Argentina",
      "goals": 6,
      "matches": [
        {
          "number": 55,
          "opponent": "Algeria",
          "date": "2026-06-16",
          "kickoff": "2026-06-17T01:00:00.000Z",
          "score": [
            3,
            0
          ],
          "goals": 3
        },
        {
          "number": 57,
          "opponent": "Austria",
          "date": "2026-06-22",
          "kickoff": "2026-06-22T17:00:00.000Z",
          "score": [
            2,
            0
          ],
          "goals": 2
        },
        {
          "number": 60,
          "opponent": "Jordan",
          "date": "2026-06-27",
          "kickoff": "2026-06-28T02:00:00.000Z",
          "score": [
            1,
            3
          ],
          "goals": 1
        }
      ],
      "profile": {
        "photo": "https://upload.wikimedia.org/wikipedia/commons/thumb/c/c8/Lionel_Messi_NE_Revolution_Inter_Miami_7.9.25-178_%28cropped_2%29.jpg/500px-Lionel_Messi_NE_Revolution_Inter_Miami_7.9.25-178_%28cropped_2%29.jpg",
        "bio": "Argentine footballer (born 1987)"
      }
    },
    {
      "name": "Erling Haaland",
      "team": "Norway",
      "goals": 4,
      "matches": [
        {
          "number": 50,
          "opponent": "Iraq",
          "date": "2026-06-16",
          "kickoff": "2026-06-16T22:00:00.000Z",
          "score": [
            1,
            4
          ],
          "goals": 2
        },
        {
          "number": 52,
          "opponent": "Senegal",
          "date": "2026-06-22",
          "kickoff": "2026-06-23T00:00:00.000Z",
          "score": [
            3,
            2
          ],
          "goals": 2
        }
      ],
      "profile": {
        "photo": "https://upload.wikimedia.org/wikipedia/commons/thumb/4/43/Erling_Haaland_Morocco_v_Norway_7_June_2026-51.jpg/500px-Erling_Haaland_Morocco_v_Norway_7_June_2026-51.jpg",
        "bio": "Norwegian footballer (born 2000)"
      }
    },
    {
      "name": "Kylian Mbappé",
      "team": "France",
      "goals": 4,
      "matches": [
        {
          "number": 49,
          "opponent": "Senegal",
          "date": "2026-06-16",
          "kickoff": "2026-06-16T19:00:00.000Z",
          "score": [
            3,
            1
          ],
          "goals": 2
        },
        {
          "number": 51,
          "opponent": "Iraq",
          "date": "2026-06-22",
          "kickoff": "2026-06-22T21:00:00.000Z",
          "score": [
            3,
            0
          ],
          "goals": 2
        }
      ],
      "profile": {
        "photo": "https://upload.wikimedia.org/wikipedia/commons/thumb/9/95/Kylian_Mbappe_France_v_Senegal_16_June_2026-391_%28cropped%29.jpg/500px-Kylian_Mbappe_France_v_Senegal_16_June_2026-391_%28cropped%29.jpg",
        "bio": "French footballer (born 1998)"
      }
    },
    {
      "name": "Ousmane Dembélé",
      "team": "France",
      "goals": 4,
      "matches": [
        {
          "number": 51,
          "opponent": "Iraq",
          "date": "2026-06-22",
          "kickoff": "2026-06-22T21:00:00.000Z",
          "score": [
            3,
            0
          ],
          "goals": 1
        },
        {
          "number": 53,
          "opponent": "Norway",
          "date": "2026-06-26",
          "kickoff": "2026-06-26T19:00:00.000Z",
          "score": [
            1,
            4
          ],
          "goals": 3
        }
      ],
      "profile": {
        "photo": "https://upload.wikimedia.org/wikipedia/commons/thumb/2/2f/Ousmane_Dembele_France_v_Senegal_16_June_2026-341_%28cropped%29.jpg/500px-Ousmane_Dembele_France_v_Senegal_16_June_2026-341_%28cropped%29.jpg",
        "bio": "French footballer (born 1997)"
      }
    },
    {
      "name": "Vinícius Júnior",
      "team": "Brazil",
      "goals": 4,
      "matches": [
        {
          "number": 13,
          "opponent": "Morocco",
          "date": "2026-06-13",
          "kickoff": "2026-06-13T22:00:00.000Z",
          "score": [
            1,
            1
          ],
          "goals": 1
        },
        {
          "number": 16,
          "opponent": "Haiti",
          "date": "2026-06-19",
          "kickoff": "2026-06-20T00:30:00.000Z",
          "score": [
            3,
            0
          ],
          "goals": 1
        },
        {
          "number": 17,
          "opponent": "Scotland",
          "date": "2026-06-24",
          "kickoff": "2026-06-24T22:00:00.000Z",
          "score": [
            0,
            3
          ],
          "goals": 2
        }
      ],
      "profile": {
        "photo": "https://upload.wikimedia.org/wikipedia/commons/thumb/1/10/Vin%C3%ADcius_J%C3%BAnior_Brazil_V_Morocco_13_June_2026-207_%28cropped%29.jpg/500px-Vin%C3%ADcius_J%C3%BAnior_Brazil_V_Morocco_13_June_2026-207_%28cropped%29.jpg",
        "bio": "Brazilian footballer (born 2000)"
      }
    },
    {
      "name": "Brian Brobbey",
      "team": "Netherlands",
      "goals": 3,
      "matches": [
        {
          "number": 33,
          "opponent": "Sweden",
          "date": "2026-06-20",
          "kickoff": "2026-06-20T17:00:00.000Z",
          "score": [
            5,
            1
          ],
          "goals": 2
        },
        {
          "number": 36,
          "opponent": "Tunisia",
          "date": "2026-06-25",
          "kickoff": "2026-06-25T23:00:00.000Z",
          "score": [
            1,
            3
          ],
          "goals": 1
        }
      ],
      "profile": {
        "photo": "https://upload.wikimedia.org/wikipedia/commons/thumb/0/0b/GAE_-_Ajax_-_52788469380_%28Brobbey%29.jpg/500px-GAE_-_Ajax_-_52788469380_%28Brobbey%29.jpg",
        "bio": "Dutch footballer (born 2002)"
      }
    },
    {
      "name": "Deniz Undav",
      "team": "Germany",
      "goals": 3,
      "matches": [
        {
          "number": 25,
          "opponent": "Curaçao",
          "date": "2026-06-14",
          "kickoff": "2026-06-14T17:00:00.000Z",
          "score": [
            7,
            1
          ],
          "goals": 1
        },
        {
          "number": 27,
          "opponent": "Ivory Coast",
          "date": "2026-06-20",
          "kickoff": "2026-06-20T20:00:00.000Z",
          "score": [
            2,
            1
          ],
          "goals": 2
        }
      ],
      "profile": {
        "photo": "https://upload.wikimedia.org/wikipedia/commons/thumb/a/a5/Deniz_undav.jpg/500px-Deniz_undav.jpg",
        "bio": "German footballer (born 1996)"
      }
    },
    {
      "name": "Elijah Just",
      "team": "New Zealand",
      "goals": 3,
      "matches": [
        {
          "number": 38,
          "opponent": "Iran",
          "date": "2026-06-15",
          "kickoff": "2026-06-16T01:00:00.000Z",
          "score": [
            2,
            2
          ],
          "goals": 2
        },
        {
          "number": 42,
          "opponent": "Belgium",
          "date": "2026-06-26",
          "kickoff": "2026-06-27T03:00:00.000Z",
          "score": [
            1,
            5
          ],
          "goals": 1
        }
      ],
      "profile": {
        "photo": "https://upload.wikimedia.org/wikipedia/commons/thumb/8/82/Elijah_Just_%28cropped%29.jpg/500px-Elijah_Just_%28cropped%29.jpg",
        "bio": "New Zealand footballer (born 2000)"
      }
    },
    {
      "name": "Harry Kane",
      "team": "England",
      "goals": 3,
      "matches": [
        {
          "number": 67,
          "opponent": "Croatia",
          "date": "2026-06-17",
          "kickoff": "2026-06-17T20:00:00.000Z",
          "score": [
            4,
            2
          ],
          "goals": 2
        },
        {
          "number": 71,
          "opponent": "Panama",
          "date": "2026-06-27",
          "kickoff": "2026-06-27T21:00:00.000Z",
          "score": [
            0,
            2
          ],
          "goals": 1
        }
      ],
      "profile": {
        "photo": "https://upload.wikimedia.org/wikipedia/commons/thumb/f/f0/The_Prime_Minister_at_St_George%27s_Park_with_Gareth_Southgate_on_October_10%2C_2023_%28Harry_Kane%29.jpg/500px-The_Prime_Minister_at_St_George%27s_Park_with_Gareth_Southgate_on_October_10%2C_2023_%28Harry_Kane%29.jpg",
        "bio": "English footballer (born 1993)"
      }
    },
    {
      "name": "Ismael Saibari",
      "team": "Morocco",
      "goals": 3,
      "matches": [
        {
          "number": 13,
          "opponent": "Brazil",
          "date": "2026-06-13",
          "kickoff": "2026-06-13T22:00:00.000Z",
          "score": [
            1,
            1
          ],
          "goals": 1
        },
        {
          "number": 15,
          "opponent": "Scotland",
          "date": "2026-06-19",
          "kickoff": "2026-06-19T22:00:00.000Z",
          "score": [
            0,
            1
          ],
          "goals": 1
        },
        {
          "number": 18,
          "opponent": "Haiti",
          "date": "2026-06-24",
          "kickoff": "2026-06-24T22:00:00.000Z",
          "score": [
            4,
            2
          ],
          "goals": 1
        }
      ],
      "profile": {
        "photo": "https://upload.wikimedia.org/wikipedia/commons/thumb/4/46/Ismael_Saibari_Brazil_V_Morocco_13_June_2026-152.jpg/500px-Ismael_Saibari_Brazil_V_Morocco_13_June_2026-152.jpg",
        "bio": "Moroccan footballer (born 2001)"
      }
    },
    {
      "name": "Ismaïla Sarr",
      "team": "Senegal",
      "goals": 3,
      "matches": [
        {
          "number": 52,
          "opponent": "Norway",
          "date": "2026-06-22",
          "kickoff": "2026-06-23T00:00:00.000Z",
          "score": [
            3,
            2
          ],
          "goals": 2
        },
        {
          "number": 54,
          "opponent": "Iraq",
          "date": "2026-06-26",
          "kickoff": "2026-06-26T19:00:00.000Z",
          "score": [
            5,
            0
          ],
          "goals": 1
        }
      ],
      "profile": {
        "photo": "",
        "bio": "Senegal國家隊球員，本屆世界盃目前攻進 3 球。"
      }
    },
    {
      "name": "Johan Manzambi",
      "team": "Switzerland",
      "goals": 3,
      "matches": [
        {
          "number": 9,
          "opponent": "Bosnia & Herzegovina",
          "date": "2026-06-18",
          "kickoff": "2026-06-18T19:00:00.000Z",
          "score": [
            4,
            1
          ],
          "goals": 2
        },
        {
          "number": 11,
          "opponent": "Canada",
          "date": "2026-06-24",
          "kickoff": "2026-06-24T19:00:00.000Z",
          "score": [
            2,
            1
          ],
          "goals": 1
        }
      ],
      "profile": {
        "photo": "",
        "bio": "Switzerland國家隊球員，本屆世界盃目前攻進 3 球。"
      }
    },
    {
      "name": "Jonathan David",
      "team": "Canada",
      "goals": 3,
      "matches": [
        {
          "number": 10,
          "opponent": "Qatar",
          "date": "2026-06-18",
          "kickoff": "2026-06-18T22:00:00.000Z",
          "score": [
            6,
            0
          ],
          "goals": 3
        }
      ],
      "profile": {
        "photo": "",
        "bio": "Canada國家隊球員，本屆世界盃目前攻進 3 球。"
      }
    },
    {
      "name": "Matheus Cunha",
      "team": "Brazil",
      "goals": 3,
      "matches": [
        {
          "number": 16,
          "opponent": "Haiti",
          "date": "2026-06-19",
          "kickoff": "2026-06-20T00:30:00.000Z",
          "score": [
            3,
            0
          ],
          "goals": 2
        },
        {
          "number": 17,
          "opponent": "Scotland",
          "date": "2026-06-24",
          "kickoff": "2026-06-24T22:00:00.000Z",
          "score": [
            0,
            3
          ],
          "goals": 1
        }
      ],
      "profile": {
        "photo": "",
        "bio": "Brazil國家隊球員，本屆世界盃目前攻進 3 球。"
      }
    },
    {
      "name": "Yoane Wissa",
      "team": "DR Congo",
      "goals": 3,
      "matches": [
        {
          "number": 61,
          "opponent": "Portugal",
          "date": "2026-06-17",
          "kickoff": "2026-06-17T17:00:00.000Z",
          "score": [
            1,
            1
          ],
          "goals": 1
        },
        {
          "number": 66,
          "opponent": "Uzbekistan",
          "date": "2026-06-27",
          "kickoff": "2026-06-27T23:30:00.000Z",
          "score": [
            3,
            1
          ],
          "goals": 2
        }
      ],
      "profile": {
        "photo": "",
        "bio": "DR Congo國家隊球員，本屆世界盃目前攻進 3 球。"
      }
    },
    {
      "name": "Anthony Elanga",
      "team": "Sweden",
      "goals": 2,
      "matches": [
        {
          "number": 33,
          "opponent": "Netherlands",
          "date": "2026-06-20",
          "kickoff": "2026-06-20T17:00:00.000Z",
          "score": [
            5,
            1
          ],
          "goals": 1
        },
        {
          "number": 35,
          "opponent": "Japan",
          "date": "2026-06-25",
          "kickoff": "2026-06-25T23:00:00.000Z",
          "score": [
            1,
            1
          ],
          "goals": 1
        }
      ],
      "profile": {
        "photo": "",
        "bio": "Sweden國家隊球員，本屆世界盃目前攻進 2 球。"
      }
    },
    {
      "name": "Ayase Ueda",
      "team": "Japan",
      "goals": 2,
      "matches": [
        {
          "number": 34,
          "opponent": "Tunisia",
          "date": "2026-06-20",
          "kickoff": "2026-06-21T04:00:00.000Z",
          "score": [
            0,
            4
          ],
          "goals": 2
        }
      ],
      "profile": {
        "photo": "",
        "bio": "Japan國家隊球員，本屆世界盃目前攻進 2 球。"
      }
    },
    {
      "name": "Cody Gakpo",
      "team": "Netherlands",
      "goals": 2,
      "matches": [
        {
          "number": 33,
          "opponent": "Sweden",
          "date": "2026-06-20",
          "kickoff": "2026-06-20T17:00:00.000Z",
          "score": [
            5,
            1
          ],
          "goals": 2
        }
      ],
      "profile": {
        "photo": "",
        "bio": "Netherlands國家隊球員，本屆世界盃目前攻進 2 球。"
      }
    },
    {
      "name": "Cristiano Ronaldo",
      "team": "Portugal",
      "goals": 2,
      "matches": [
        {
          "number": 63,
          "opponent": "Uzbekistan",
          "date": "2026-06-23",
          "kickoff": "2026-06-23T17:00:00.000Z",
          "score": [
            5,
            0
          ],
          "goals": 2
        }
      ],
      "profile": {
        "photo": "",
        "bio": "Portugal國家隊球員，本屆世界盃目前攻進 2 球。"
      }
    },
    {
      "name": "Crysencio Summerville",
      "team": "Netherlands",
      "goals": 2,
      "matches": [
        {
          "number": 31,
          "opponent": "Japan",
          "date": "2026-06-14",
          "kickoff": "2026-06-14T20:00:00.000Z",
          "score": [
            2,
            2
          ],
          "goals": 1
        },
        {
          "number": 33,
          "opponent": "Sweden",
          "date": "2026-06-20",
          "kickoff": "2026-06-20T17:00:00.000Z",
          "score": [
            5,
            1
          ],
          "goals": 1
        }
      ],
      "profile": {
        "photo": "",
        "bio": "Netherlands國家隊球員，本屆世界盃目前攻進 2 球。"
      }
    },
    {
      "name": "Cyle Larin",
      "team": "Canada",
      "goals": 2,
      "matches": [
        {
          "number": 7,
          "opponent": "Bosnia & Herzegovina",
          "date": "2026-06-12",
          "kickoff": "2026-06-12T19:00:00.000Z",
          "score": [
            1,
            1
          ],
          "goals": 1
        },
        {
          "number": 10,
          "opponent": "Qatar",
          "date": "2026-06-18",
          "kickoff": "2026-06-18T22:00:00.000Z",
          "score": [
            6,
            0
          ],
          "goals": 1
        }
      ],
      "profile": {
        "photo": "",
        "bio": "Canada國家隊球員，本屆世界盃目前攻進 2 球。"
      }
    },
    {
      "name": "Daichi Kamada",
      "team": "Japan",
      "goals": 2,
      "matches": [
        {
          "number": 31,
          "opponent": "Netherlands",
          "date": "2026-06-14",
          "kickoff": "2026-06-14T20:00:00.000Z",
          "score": [
            2,
            2
          ],
          "goals": 1
        },
        {
          "number": 34,
          "opponent": "Tunisia",
          "date": "2026-06-20",
          "kickoff": "2026-06-21T04:00:00.000Z",
          "score": [
            0,
            4
          ],
          "goals": 1
        }
      ],
      "profile": {
        "photo": "",
        "bio": "Japan國家隊球員，本屆世界盃目前攻進 2 球。"
      }
    },
    {
      "name": "Daniel Muñoz",
      "team": "Colombia",
      "goals": 2,
      "matches": [
        {
          "number": 62,
          "opponent": "Uzbekistan",
          "date": "2026-06-17",
          "kickoff": "2026-06-18T02:00:00.000Z",
          "score": [
            1,
            3
          ],
          "goals": 1
        },
        {
          "number": 64,
          "opponent": "DR Congo",
          "date": "2026-06-23",
          "kickoff": "2026-06-24T02:00:00.000Z",
          "score": [
            1,
            0
          ],
          "goals": 1
        }
      ],
      "profile": {
        "photo": "",
        "bio": "Colombia國家隊球員，本屆世界盃目前攻進 2 球。"
      }
    },
    {
      "name": "Ermin Mahmic",
      "team": "Bosnia & Herzegovina",
      "goals": 2,
      "matches": [
        {
          "number": 9,
          "opponent": "Switzerland",
          "date": "2026-06-18",
          "kickoff": "2026-06-18T19:00:00.000Z",
          "score": [
            4,
            1
          ],
          "goals": 1
        },
        {
          "number": 12,
          "opponent": "Qatar",
          "date": "2026-06-24",
          "kickoff": "2026-06-24T19:00:00.000Z",
          "score": [
            3,
            1
          ],
          "goals": 1
        }
      ],
      "profile": {
        "photo": "",
        "bio": "Bosnia & Herzegovina國家隊球員，本屆世界盃目前攻進 2 球。"
      }
    }
  ],
  "news": [
    {
      "title": "世足賽／傷停補時攻入關鍵一球！巴西2：1絕殺日本| 2026美加墨世足| 運動 - UDN",
      "link": "https://news.google.com/rss/articles/CBMiU0FVX3lxTFBXLURWSFluel9QdU9WUWhpVC1GVFIzQ2xJWWdrN0FNYzBoSkRDYUZMTEQ2WEd5dTE2alhDOG1nYUlBT29ZNXJiWUlnbV9ZaXNDVU53?oc=5",
      "pubDate": "Mon, 29 Jun 2026 19:25:20 GMT",
      "source": "UDN"
    },
    {
      "title": "2026 世界盃足球賽 06/30【德國 vs 巴拉圭】直播、轉播 LIVE 線上看 - 蘋果仁",
      "link": "https://news.google.com/rss/articles/CBMiTEFVX3lxTE1yWm0zUGhxaU1LeXNiSUdRMVdUNzBWakJDSHg5akpYSHhPUWZ6cldpbmR4a0pWeDRNWmZrNjR5TDRidm1kaHBVbkhpV1U?oc=5",
      "pubDate": "Mon, 29 Jun 2026 18:32:02 GMT",
      "source": "蘋果仁"
    },
    {
      "title": "世足》日本隊夢碎！馬丁內利絕殺率巴西逆轉闖16強 - 自由體育",
      "link": "https://news.google.com/rss/articles/CBMiYEFVX3lxTFBnRGs0S24zcV9vM2UxUWxqVmQ4UV95TEJ1UW5sdkQ1dW80aWZwX3VNQzgxVVdIUjNjZ093bVZ3ZkQtX0RQYzYtOXFDTUlVSHZ0RkhQdFgxa3Y0QmZsX1pNR9IBZkFVX3lxTFBWd2wydEl5VWVsSVpPTHU2NkxkVndXc1pfcHlrZUFjM1oxcU1UOEhxcjJMTVFuRjA3ZDBtY0ZKUzNzclYxMHV3WTN4YzFLc2lGUjlJMnBoaG1jcjNMSC1fMXkwb01kZw?oc=5",
      "pubDate": "Mon, 29 Jun 2026 22:07:49 GMT",
      "source": "自由體育"
    },
    {
      "title": "2026 世界盃足球賽 06/30【巴西 vs 日本】直播、轉播 LIVE 線上看 - 蘋果仁",
      "link": "https://news.google.com/rss/articles/CBMiTEFVX3lxTE5qdXNnbnlySjNjS1ZacHR5YlZ2NlBEb3RVVkZnSkt5SV9XM3ItZURlTWM5ZXkyQ00yVmlJQk1MaldWUjJFSzR4ZXl1cVg?oc=5",
      "pubDate": "Mon, 29 Jun 2026 20:48:04 GMT",
      "source": "蘋果仁"
    },
    {
      "title": "【巴西vs日本】06/30世足直播！獨家免費線上看、LIVE！2026世界盃 轉播 - 吃貨瑪莉",
      "link": "https://news.google.com/rss/articles/CBMiPEFVX3lxTE1iZF8wZmFuaktMVll5dm44V0lacWRWOFBmWmRpRjJRYmJtcDhTREJIalpoOHhRSlpHSjJKeQ?oc=5",
      "pubDate": "Mon, 29 Jun 2026 15:32:23 GMT",
      "source": "吃貨瑪莉"
    },
    {
      "title": "2026世足／32強淘汰賽對戰表出爐！殘酷賽制「輸球即回家」 首戰加拿大1：0絕殺南非 - Yahoo新聞",
      "link": "https://news.google.com/rss/articles/CBMioANBVV95cUxOMUZzaUNXeFdfTEJBY3FkdkRSWEZXRVV4ZlpvLTRqRGRHbVYzZEwwYVFYcV9NMmVzQW5Xa0FmckpZZ2NBNFB0alYzeWczMXdVNVpYdmN2SlVPZjlWNnJTdVVlN2tTSTRuajg0b1JJMkthZGFNUC1SQ2lkWEZzU3phZURjWXd4TXg4Zjd3LUhzMXFocWs0cUc4M3ZKakRIREFvajhQejM5MDQzT1o3UDFoOTRPZUJKS1JJTDBmOFh5Y3AzVDZSUzVObHpHNEUtZDZTR3IzanJ5QlFNQ0ZWOHc2c0ZDQnNETzM0Y0g4SlhnUFZINTRkbF9nSmF6ejJPUEpfckF5cHk2ZW5ocXo4SlVET0UtOVJmdktSXzhqeFNQVHR4Vkl4WjRTSFBlU0FhT1drdnp3b0EyZDdRNXJKSXZOTEQ5cnJ4QTN0X1VRSHRlUTR3RFhlcWk5cVBMRW5oZm5McjNsZjhZT2h5ZlJqWHE3a1YyYjgwY29KVTlMMFNQRUk5TG92MFRnTF9HcTA5OHYyZWVGa1R6akw0N01aNmZSZA?oc=5",
      "pubDate": "Mon, 29 Jun 2026 01:30:41 GMT",
      "source": "Yahoo新聞"
    },
    {
      "title": "日本巴西直播線上看｜世界盃32強日本vs巴西比賽時間、轉播平台 - Marie Claire 美麗佳人",
      "link": "https://news.google.com/rss/articles/CBMiYEFVX3lxTE4xdkVVTWJmcDZrWXo0azVYVlZwQ2QyM3p0TTJjZzRFZWNFTGZlc3ZvTjJtYnNXZWx6NU9QWm4taTJHWXlFcWJzQTlCU1hqdnRBN3lqRnNlVEN4ekR0VGx0UQ?oc=5",
      "pubDate": "Mon, 29 Jun 2026 19:27:59 GMT",
      "source": "Marie Claire 美麗佳人"
    },
    {
      "title": "世界盃6/30荷蘭VS摩洛哥32強淘汰賽懶人包》全分析、預測先發名單 - NOWnews今日新聞",
      "link": "https://news.google.com/rss/articles/CBMiTEFVX3lxTE5Ta2VSZjhxOEdLYVR1cExHdVhCQ1Y4YUNIQzF0emMxRXg4S3FMcG5HNFRNQ0N4YTVNaE5xQ3VQWE9tSUtIZ0lXNUIzOWbSAVJBVV95cUxQUnVLRE12Yjdia00weWlKXzFucFdldWN6ckx4bHE4YnJ0TjlxZ2lpclo2cXZON3E4cmZEWUVGNGVZQ0M1WkZ0ZlNMcWNUbEx1Nk5n?oc=5",
      "pubDate": "Sun, 28 Jun 2026 23:25:05 GMT",
      "source": "NOWnews今日新聞"
    },
    {
      "title": "《2026世界盃》完成真正的團隊進化 小組賽後法國為何成為最大奪冠熱門？ _p.2 - 足球 - 運動視界Sports Vision",
      "link": "https://news.google.com/rss/articles/CBMiWkFVX3lxTE5tT1N5Q2NPbDVXQ1FBV2RZcklFSHVGb3BmaTRyS2JlSkpyUFpxUldwZXROTWF4eVdqV0k1VmtwblYxOUtFTF83dHMzMVJ1X19EX0NUTEZLQmRFdw?oc=5",
      "pubDate": "Sun, 28 Jun 2026 16:10:46 GMT",
      "source": "運動視界Sports Vision"
    }
  ],
  "odds": [
    {
      "home": "Germany",
      "away": "Paraguay",
      "homePrice": 1.85,
      "drawPrice": 2.2,
      "awayPrice": 11
    },
    {
      "home": "Netherlands",
      "away": "Morocco",
      "homePrice": 2.4,
      "drawPrice": 3.1,
      "awayPrice": 3.45
    },
    {
      "home": "Ivory Coast",
      "away": "Norway",
      "homePrice": 3.7,
      "drawPrice": 3.45,
      "awayPrice": 2.02
    },
    {
      "home": "France",
      "away": "Sweden",
      "homePrice": 1.29,
      "drawPrice": 6.2,
      "awayPrice": 11
    },
    {
      "home": "Mexico",
      "away": "Ecuador",
      "homePrice": 2.28,
      "drawPrice": 2.9,
      "awayPrice": 4.2
    },
    {
      "home": "England",
      "away": "DR Congo",
      "homePrice": 1.28,
      "drawPrice": 5.5,
      "awayPrice": 15
    },
    {
      "home": "Belgium",
      "away": "Senegal",
      "homePrice": 2.2,
      "drawPrice": 3.3,
      "awayPrice": 3.4
    },
    {
      "home": "USA",
      "away": "Bosnia & Herzegovina",
      "homePrice": 1.39,
      "drawPrice": 5.3,
      "awayPrice": 10
    },
    {
      "home": "Spain",
      "away": "Austria",
      "homePrice": 1.27,
      "drawPrice": 5.1,
      "awayPrice": 12
    },
    {
      "home": "Portugal",
      "away": "Croatia",
      "homePrice": 1.76,
      "drawPrice": 3.65,
      "awayPrice": 4.6
    },
    {
      "home": "Switzerland",
      "away": "Algeria",
      "homePrice": 2.05,
      "drawPrice": 3.2,
      "awayPrice": 4
    },
    {
      "home": "Australia",
      "away": "Egypt",
      "homePrice": 3.6,
      "drawPrice": 2.9,
      "awayPrice": 2.43
    },
    {
      "home": "Argentina",
      "away": "Cape Verde",
      "homePrice": 1.16,
      "drawPrice": 9,
      "awayPrice": 20
    },
    {
      "home": "Colombia",
      "away": "Ghana",
      "homePrice": 1.45,
      "drawPrice": 4,
      "awayPrice": 8.5
    }
  ],
  "videos": [
    {
      "id": "TVktH1xPfWg",
      "title": "【2026 FIFA世界盃™】巴西逆轉日本 主帥說明內馬爾使用時機/愛爾達電視20260630",
      "label": "愛爾達體育家族 ELTA Sports・繁中精華",
      "url": "https://www.youtube.com/watch?v=TVktH1xPfWg"
    },
    {
      "id": "YagVi6GsvuM",
      "title": "【2026 FIFA世界盃™】巴西補時致勝勁射 逆轉日本晉級16強/愛爾達電視20260630",
      "label": "愛爾達體育家族 ELTA Sports・繁中精華",
      "url": "https://www.youtube.com/watch?v=YagVi6GsvuM"
    },
    {
      "id": "WebmD83jlfs",
      "title": "【全場精華】巴西 VS 日本 32強｜2026 FIFA世界盃™｜鎖定ELTA tv愛爾達",
      "label": "愛爾達體育家族 ELTA Sports・繁中精華",
      "url": "https://www.youtube.com/watch?v=WebmD83jlfs"
    }
  ]
}
